MANIFEST.in
README.rst
setup.py
djangocms_comments/__init__.py
djangocms_comments/admin.py
djangocms_comments/cms_plugins.py
djangocms_comments/fields.py
djangocms_comments/forms.py
djangocms_comments/models.py
djangocms_comments/settings.py
djangocms_comments/spam.py
djangocms_comments/urls.py
djangocms_comments/views.py
djangocms_comments/widgets.py
djangocms_comments.egg-info/PKG-INFO
djangocms_comments.egg-info/SOURCES.txt
djangocms_comments.egg-info/dependency_links.txt
djangocms_comments.egg-info/not-zip-safe
djangocms_comments.egg-info/top_level.txt
djangocms_comments/boilerplates/bootstrap3/static/djangocms_comments/dist/css/comments.css
djangocms_comments/boilerplates/bootstrap3/static/djangocms_comments/dist/img/unpublished.png
djangocms_comments/boilerplates/bootstrap3/static/djangocms_comments/src/css/comments.css
djangocms_comments/boilerplates/bootstrap3/static/djangocms_comments/src/css/comments.css.map
djangocms_comments/boilerplates/bootstrap3/static/djangocms_comments/src/img/unpublished.png
djangocms_comments/boilerplates/bootstrap3/static/djangocms_comments/src/scss/_variables.scss
djangocms_comments/boilerplates/bootstrap3/static/djangocms_comments/src/scss/comments.scss
djangocms_comments/boilerplates/bootstrap3/templates/djangocms_comments/comment.html
djangocms_comments/boilerplates/bootstrap3/templates/djangocms_comments/comment_box.html
djangocms_comments/boilerplates/bootstrap3/templates/djangocms_comments/comments.html
djangocms_comments/migrations/0001_initial.py
djangocms_comments/migrations/__init__.py
djangocms_comments/static/djangocms_comments/dist/css/admin-with-bootstrap.css
djangocms_comments/static/djangocms_comments/dist/css/admin-without-bootstrap.css
djangocms_comments/static/djangocms_comments/dist/js/comments.min.js
djangocms_comments/static/djangocms_comments/img/unpublished.png
djangocms_comments/static/djangocms_comments/src/css/admin-with-bootstrap.css
djangocms_comments/static/djangocms_comments/src/css/admin-without-bootstrap.css
djangocms_comments/static/djangocms_comments/src/js/comments.js
djangocms_comments/static/djangocms_comments/src/scss/_light-bootstrap.scss
