Metadata-Version: 1.1
Name: djangocms-comments
Version: 0.2.3
Summary: A comment system for Django CMS unintrusive and easy to use.
